wyze_scale_tool/__init__.py
wyze_scale_tool/cli.py
wyze_scale_tool/wyze_scale.py
wyze_scale_tool-1.0.0.dist-info/METADATA
wyze_scale_tool-1.0.0.dist-info/WHEEL
wyze_scale_tool-1.0.0.dist-info/entry_points.txt
wyze_scale_tool-1.0.0.dist-info/licenses/LICENSE
wyze_scale_tool-1.0.0.dist-info/RECORD
