Metadata-Version: 2.1
Name: wyze_scale_tool
Version: 1.0.0
Summary: A utility for reading from and managing a Wyze Scale X
Project-URL: Homepage, https://github.com/jesusfreke/wyze_scale_tool
Author-email: Ben Gruver <jesusfreke@jesusfreke.com>
License-Expression: BSD-2-Clause
License-File: LICENSE
Keywords: scale,wyze,wyze scale x
Classifier: License :: OSI Approved :: BSD License
Classifier: Operating System :: OS Independent
Classifier: Programming Language :: Python :: 3
Classifier: Topic :: Home Automation
Requires-Python: >=3.8
Requires-Dist: bleak
Requires-Dist: xxtea
